spinWannier/WannierTBmodel.py
spinWannier/__init__.py
spinWannier/test_spn_file.py
spinWannier/vaspspn.py
spinWannier/wannier_quality_utils.py
spinWannier/wannier_utils.py
spinWannier-0.1.7.dist-info/LICENSE
spinWannier-0.1.7.dist-info/METADATA
spinWannier-0.1.7.dist-info/WHEEL
spinWannier-0.1.7.dist-info/top_level.txt
spinWannier-0.1.7.dist-info/RECORD
