Metadata-Version: 2.1
Name: spinWannier
Version: 0.1.7
Summary: Wannier (spin) interpolation and spin texture plotting
Author: L. Vojáček
Author-email: Libor.Vojacek@vutbr.cz
License: BSD 3-Clause License
License-File: LICENSE
Requires-Dist: numpy
Requires-Dist: matplotlib
Requires-Dist: scipy
Requires-Dist: pandas
Requires-Dist: pytest
Requires-Dist: pytest-cov
Requires-Dist: pytest-mpl
